[
	{
				"name": "Common Chest",
				"cost": 50,
				"emoji": "<:CommonBox:727513141260583031>",
				"rarity": "common",
				"picture": "common_closed.png",
				"ctg": "chests",
				"description": "Common Chest."
	},
	{
				"name": "Rare Chest",
				"cost": 300,
				"emoji": "<:RareBox:727513141243805776>",
				"rarity": "rare",
				"picture": "rare_closed.png",
				"ctg": "chests",
				"description": "Rare Chest."
	},
	{
				"name": "Epic Chest",
				"cost": 1400,
				"emoji": "<:EpicBox:727513140849410090>",
				"rarity": "epic",
				"picture": "epic_closed.png",
				"ctg": "chests",
				"description": "Epic Chest."
	},
	{
				"name": "Legendary Chest",
				"cost": 8000,
				"emoji": "<:LegendaryBox:727513140836827247>",
				"rarity": "legendary",
				"picture": "legendary_closed.png",
				"ctg": "chests",
				"description": "Legendary Chest."
	},
	{
				"name": "Mana Potion",
				"cost": null,
				"emoji": "<:Manapotion:727508079469396028>",
				"rarity": "rare",
				"picture": "mp.png",
				"ctg": "consumable",
				"description": "Mana Potion."
	},
	{
				"name": "Lesser Mana Potion",
				"cost": null,
				"emoji": "<:Lessermanapotion:727508079578710178>",
				"rarity": "uncommon",
				"picture": "lmp.png",
				"ctg": "consumable",
				"description": "Lesser Mana Potion."
	},
	{
				"name": "Greater Mana potion",
				"cost": null,
				"emoji": "<:Greatermanapotion:727508080316907561>",
				"rarity": "epic",
				"picture": "gmp.png",
				"ctg": "consumable",
				"description": "Greater Mana potion."
	},
	{
				"name": "Healing Potion",
				"cost": null,
				"emoji": "<:Healingpotion:727508079498756246>",
				"rarity": "rare",
				"picture": "hp.png",
				"ctg": "consumable",
				"description": "Healing Potion."
	},
	{
				"name": "Lesser Healing Potion",
				"cost": null,
				"emoji": "<:Lesserhealingpotion:727508079448686622>",
				"rarity": "uncommon",
				"picture": "lhp.png",
				"ctg": "consumable",
				"description": "Lesser Healing Potion."
	},
	{
				"name": "Greater Healing Potion",
				"cost": null,
				"emoji": "<:GreaterHealingpotion:727508079494692914>",
				"rarity": "epic",
				"picture": "ghp.png",
				"ctg": "consumable",
				"description": "Greater Healing Potion."
	},
	{
				"name": "Tea",
				"cost": 2,
				"emoji": "🍵",
				"rarity": "common",
				"picture": null,
				"ctg": "consumable",
				"description": "its tea innit."
	},
	{
				"name": "Coffee",
				"cost": 3,
				"emoji": "☕",
				"rarity": "common",
				"picture": null,
				"ctg": "consumable",
				"description": "its Coffee innit."
	},
	{
				"name": "Cake",
				"cost": 6,
				"emoji": "🍰",
				"rarity": "common",
				"picture": null,
				"ctg": "consumable",
				"description": "its Cake innit."
	},
	{
				"name": "Gun",
				"cost": 30,
				"emoji": "<:gun:727585753818857563>",
				"rarity": "uncommon",
				"picture": "gun.png",
				"ctg": "consumable",
				"description": "You can use this with the __steal__ command to steal money from other users."
	},
	{
				"name": "Steal Protection",
				"emoji": "🛡️",
				"rarity": "rare",
				"picture": null,
				"cost": 80,
				"ctg": "consumable",
				"description": "You can use this to gain 8 hours of protection against stealing.\nThis item stacks."
	},
	{
				"name": "Profile Colour",
				"cost": 40,
				"emoji": "🌈",
				"rarity": "uncommon",
				"picture": null,
				"ctg": "consumable",
				"description": "Use this to alter the white border on the left of all your commands."
	},
	{
				"name": "Star",
				"cost": 10000,
				"emoji": "⭐",
				"rarity": "legendary",
				"picture": null,
				"ctg": "collectables",
				"description": "Gives you passive income."
	},
	{
				"name": "Museum",
				"cost": 5000,
				"emoji": "🏛️",
				"rarity": "epic",
				"picture": null,
				"ctg": "collectables",
				"description": "Gives you passive income."
	},
	{
				"name": "House",
				"cost": 1000,
				"emoji": "🏡",
				"rarity": "epic",
				"picture": null,
				"ctg": "collectables",
				"description": "Gives you passive income."
	},
	{
				"name": "Car",
				"cost": 65,
				"emoji": "🚗",
				"rarity": "common",
				"picture": null,
				"ctg": "collectables",
				"description": "Gives you passive income."
	},
	{
				"name": "Motorcycle",
				"cost": 40,
				"emoji": "🏍️",
				"rarity": "common",
				"picture": null,
				"ctg": "collectables",
				"description": "Gives you passive income."
	},
	{
				"name": "Jet plane",
				"cost":700,
				"emoji": "✈️",
				"rarity": "rare",
				"picture": null,
				"ctg": "collectables",
				"description": "Gives you passive income."
	},
	{
				"name": "Prop plane",
				"cost": 300,
				"emoji": "🛩️",
				"rarity": "rare",
				"picture": null,
				"ctg": "collectables",
				"description": "Gives you passive income."
	},
	{
				"name": "Sailboat",
				"cost": 200,
				"emoji": "⛵",
				"rarity": "uncommon",
				"picture": null,
				"ctg": "collectables",
				"description": "Gives you passive income."
	},
	{
				"name": "Motorboat",
				"cost": 125,
				"emoji": "🚤",
				"rarity": "uncommon",
				"picture": null,
				"ctg": "collectables",
				"description": "Gives you passive income."
	},
	{
				"name": "Office",
				"cost": 50000,
				"emoji": "🏢",
				"rarity": "legendary",
				"picture": null,
				"ctg": "collectables",
				"description": "Gives you passive income."
	}
]